datapackage_pipelines_metrics/__init__.py
datapackage_pipelines_metrics/influxdb.py
datapackage_pipelines_metrics/processors/__init__.py
datapackage_pipelines_metrics/processors/send.py
datapackage_pipelines_metrics-0.1.3.dist-info/DESCRIPTION.rst
datapackage_pipelines_metrics-0.1.3.dist-info/METADATA
datapackage_pipelines_metrics-0.1.3.dist-info/RECORD
datapackage_pipelines_metrics-0.1.3.dist-info/WHEEL
datapackage_pipelines_metrics-0.1.3.dist-info/metadata.json
datapackage_pipelines_metrics-0.1.3.dist-info/top_level.txt
