Metadata-Version: 2.0
Name: datapackage-pipelines-metrics
Version: 0.1.3
Summary: UNKNOWN
Home-page: https://github.com/OriHoch/datapackage-pipelines-metrics
Author: UNKNOWN
Author-email: UNKNOWN
License: MIT
Platform: UNKNOWN
Requires-Dist: datapackage-pipelines
Requires-Dist: requests
